{
  "users": [
    {
      "name": "john",
      "profil_img": "/src/assets/user.svg",
      "id": 1
    }
  ],
  "calls": [
    {
      "id": 1,
      "name": "John Elvis",
      "contry": "United States",
      "flag": "/src/assets/flag.png",
      "profil_img": "/src/assets/user.svg",
      "language": "French",
      "occupation": "Freelance",
      "objective": "Fluent",
      "subscription": "Free Trial",
      "selected": true
    },
    {
      "id": 2,
      "name": "John Elvis",
      "contry": "United States",
      "flag": "/src/assets/flag.png",
      "profil_img": "/src/assets/user.svg",
      "language": "French",
      "occupation": "Freelance",
      "objective": "Fluent",
      "subscription": "Free Trial",
      "selected": "foo"
    },
    {
      "id": 3,
      "name": "John Elvis",
      "contry": "United States",
      "flag": "/src/assets/flag.png",
      "profil_img": "/src/assets/user.svg",
      "language": "French",
      "occupation": "Freelance",
      "objective": "Fluent",
      "subscription": "Free Trial",
      "selected": true
    },
    {
      "data": {
        "id": 4,
        "name": "ekekkkekke"
      },
      "id": 4
    },
    {
      "id": 5,
      "name": "John Elvis",
      "contry": "United States",
      "flag": "/src/assets/flag.png",
      "profil_img": "/src/assets/user.svg",
      "language": "French",
      "occupation": "Freelance",
      "objective": "Fluent",
      "subscription": "Free Trial",
      "selected": true
    },
    {
      "id": 6,
      "name": "John Elvis",
      "contry": "United States",
      "flag": "/src/assets/flag.png",
      "profil_img": "/src/assets/user.svg",
      "language": "French",
      "occupation": "Freelance",
      "objective": "Fluent",
      "subscription": "Free Trial",
      "selected": true
    },
    {
      "id": 7,
      "name": "jeejjejjejej"
    },
    {
      "data": {
        "id": 8,
        "name": "John Elviseeee]",
        "contry": "United States",
        "language": "French",
        "occupation": "Freelance",
        "objective": "Fluent",
        "subscription": "Free Trial"
      },
      "id": 8
    }
  ]
}